libname/FileMaster.py
libname/__init__.py
mqtt_file_logger-0.0.10.dist-info/METADATA
mqtt_file_logger-0.0.10.dist-info/WHEEL
mqtt_file_logger-0.0.10.dist-info/top_level.txt
mqtt_file_logger-0.0.10.dist-info/RECORD
